np4k/__init__.py
np4k/api.py
np4k/article.py
np4k/cleaners.py
np4k/configuration.py
np4k/exceptions.py
np4k/extractors.py
np4k/images.py
np4k/lib.py
np4k/mthreading.py
np4k/network.py
np4k/nlp.py
np4k/outputformatters.py
np4k/parsers.py
np4k/settings.py
np4k/source.py
np4k/text.py
np4k/urls.py
np4k/utils.py
np4k/version.py
np4k/resources/misc/google_sources.txt
np4k/resources/misc/popular_sources.txt
np4k/resources/misc/stopwords-nlp-en.txt
np4k/resources/misc/useragents.txt
np4k/resources/text/stopwords-ar.txt
np4k/resources/text/stopwords-be.txt
np4k/resources/text/stopwords-bg.txt
np4k/resources/text/stopwords-da.txt
np4k/resources/text/stopwords-de.txt
np4k/resources/text/stopwords-el.txt
np4k/resources/text/stopwords-en.txt
np4k/resources/text/stopwords-es.txt
np4k/resources/text/stopwords-et.txt
np4k/resources/text/stopwords-fa.txt
np4k/resources/text/stopwords-fi.txt
np4k/resources/text/stopwords-fr.txt
np4k/resources/text/stopwords-he.txt
np4k/resources/text/stopwords-hi.txt
np4k/resources/text/stopwords-hr.txt
np4k/resources/text/stopwords-hu.txt
np4k/resources/text/stopwords-id.txt
np4k/resources/text/stopwords-it.txt
np4k/resources/text/stopwords-ja.txt
np4k/resources/text/stopwords-ko.txt
np4k/resources/text/stopwords-lt.txt
np4k/resources/text/stopwords-mk.txt
np4k/resources/text/stopwords-nb.txt
np4k/resources/text/stopwords-nl.txt
np4k/resources/text/stopwords-no.txt
np4k/resources/text/stopwords-pl.txt
np4k/resources/text/stopwords-pt.txt
np4k/resources/text/stopwords-ro.txt
np4k/resources/text/stopwords-ru.txt
np4k/resources/text/stopwords-sl.txt
np4k/resources/text/stopwords-sr.txt
np4k/resources/text/stopwords-sv.txt
np4k/resources/text/stopwords-sw.txt
np4k/resources/text/stopwords-th.txt
np4k/resources/text/stopwords-tr.txt
np4k/resources/text/stopwords-uk.txt
np4k/resources/text/stopwords-vi.txt
np4k/resources/text/stopwords-zh.txt
np4k/videos/__init__.py
np4k/videos/extractors.py
np4k/videos/videos.py
np4k-0.0.95.dist-info/LICENSE
np4k-0.0.95.dist-info/METADATA
np4k-0.0.95.dist-info/WHEEL
np4k-0.0.95.dist-info/top_level.txt
np4k-0.0.95.dist-info/RECORD
