Metadata-Version: 2.1
Name: np4k
Version: 0.0.95
Home-page: https://github.com/airvuetech/newspaper4k/
Author: Airvue
Author-email: dev@airvue.news
Maintainer: Airvue
Maintainer-email: dev@airvue.news
Requires-Python: >=3.9,<4.0
License-File: LICENSE
Requires-Dist: beautifulsoup4 (<5.0.0,>=4.11.2)
Requires-Dist: cssselect (<2.0.0,>=1.2.0)
Requires-Dist: feedfinder2 (<0.0.5,>=0.0.4)
Requires-Dist: feedparser (<7.0.0,>=6.0.10)
Requires-Dist: jieba3k (<0.36.0,>=0.35.1)
Requires-Dist: lxml (<5.0.0,>=4.9.2)
Requires-Dist: markdownify (<0.12.0,>=0.11.6)
Requires-Dist: nltk (<4.0.0,>=3.8.1)
Requires-Dist: pillow (<10.0.0,>=9.4.0)
Requires-Dist: pythainlp (<4.0.0,>=3.1.1)
Requires-Dist: python-dateutil (<3.0.0,>=2.8.2)
Requires-Dist: pyyaml (<7.0,>=6.0)
Requires-Dist: requests (<3.0.0,>=2.28.2)
Requires-Dist: tinysegmenter (<0.5,>=0.4)
Requires-Dist: tldextract (<4.0.0,>=3.4.0)
